errant/__init__.py
errant/alignment.py
errant/annotator.py
errant/constants.py
errant/edit.py
errant/helper.py
errant/tokenizer.py
errant/utils.py
errant/api/__init__.py
errant/api/scoring.py
errant/commands/__init__.py
errant/commands/compare_m2.py
errant/commands/m2_to_m2.py
errant/commands/parallel_to_m2.py
errant/en/__init__.py
errant/en/classifier.py
errant/en/lancaster.py
errant/en/merger.py
errant/en/resources/README.md
errant/en/resources/en-ptb_map
errant/en/resources/en_GB-large.txt
errant_prep-3.2.3.dist-info/LICENSE.md
errant_prep-3.2.3.dist-info/METADATA
errant_prep-3.2.3.dist-info/WHEEL
errant_prep-3.2.3.dist-info/entry_points.txt
errant_prep-3.2.3.dist-info/top_level.txt
errant_prep-3.2.3.dist-info/RECORD
