Metadata-Version: 2.1
Name: errant-prep
Version: 3.2.3
Summary: The ERRor ANnotation Toolkit (ERRANT).         Automatically extract and classify edits in parallel sentences.
Home-page: https://github.com/chrisjbryant/errant
Author: Christopher Bryant, Mariano Felice
Author-email: christopher.bryant@cl.cam.ac.uk
License: MIT
Keywords: automatic annotation,grammatical errors,natural language processing
Classifier: Development Status :: 5 - Production/Stable
Classifier: Intended Audience :: Education
Classifier: Intended Audience :: Science/Research
Classifier: License :: OSI Approved :: MIT License
Classifier: Natural Language :: English
Classifier: Operating System :: OS Independent
Classifier: Programming Language :: Python :: 3.9
Classifier: Topic :: Education
Classifier: Topic :: Scientific/Engineering :: Artificial Intelligence
Classifier: Topic :: Scientific/Engineering :: Information Analysis
Classifier: Topic :: Text Processing :: Linguistic
Requires-Python: >= 3.9
License-File: LICENSE.md
Requires-Dist: spacy >=3
Requires-Dist: rapidfuzz >=2.0.0
